map/MapArgumentParser.py
map/MapConstants.py
map/__init__.py
map/map_argument_parser.py
map/map_constants.py
map/mapper.py
map/version.py
map-1.3.0.data/scripts/map
map-1.3.0.dist-info/DESCRIPTION.rst
map-1.3.0.dist-info/METADATA
map-1.3.0.dist-info/RECORD
map-1.3.0.dist-info/WHEEL
map-1.3.0.dist-info/metadata.json
map-1.3.0.dist-info/top_level.txt
